jumpavg/__init__.py
jumpavg/avg_stdev_stats.py
jumpavg/bit_counting_group.py
jumpavg/bit_counting_group_list.py
jumpavg/bit_counting_stats.py
jumpavg/classify.py
jumpavg/m.py
jumpavg-0.4.2.dist-info/LICENSE.txt
jumpavg-0.4.2.dist-info/METADATA
jumpavg-0.4.2.dist-info/WHEEL
jumpavg-0.4.2.dist-info/top_level.txt
jumpavg-0.4.2.dist-info/RECORD
