Metadata-Version: 2.1
Name: jumpavg
Version: 0.4.2
Summary: Library for locating changes in time series by grouping results.
Author-email: "Cisco Systems Inc. and/or its affiliates" <csit-dev@lists.fd.io>
Maintainer-email: Vratko Polak <vrpolak@cisco.com>, Tibor Frank <tifrank@cisco.com>
License: Apache License
Project-URL: Bug Tracker, https://jira.fd.io/projects/CSIT/issues
Project-URL: Source, https://gerrit.fd.io/r/gitweb?p=csit.git;a=tree;f=PyPI/jumpavg
Keywords: progression,regression,anomaly detection,statistics,bits
Classifier: Development Status :: 3 - Alpha
Classifier: Intended Audience :: Science/Research
Classifier: License :: OSI Approved :: Apache Software License
Classifier: Natural Language :: English
Classifier: Operating System :: OS Independent
Classifier: Programming Language :: Python :: 3.8
Classifier: Topic :: Scientific/Engineering :: Information Analysis
Requires-Python: >=3.8
License-File: LICENSE.txt
